MonsterFactory/__init__.py
MonsterFactory/monster.py
MonsterFactory/monster_lib.py
MonsterFactory-0.0.5.dist-info/METADATA
MonsterFactory-0.0.5.dist-info/WHEEL
MonsterFactory-0.0.5.dist-info/top_level.txt
MonsterFactory-0.0.5.dist-info/RECORD
